prasadD/__init__.py
prasadD/prasadD.py
prasadD-1.0.dist-info/METADATA
prasadD-1.0.dist-info/WHEEL
prasadD-1.0.dist-info/top_level.txt
prasadD-1.0.dist-info/RECORD
