Metadata-Version: 2.1
Name: prasadD
Version: 1.0
Summary: addition of three numbers
Author: prasad
License: MIT
